micro_http_server/__init__.py
micro_http_server/userver.py
micro_http_server-0.1.1.dist-info/licenses/LICENSE
micro_http_server-0.1.1.dist-info/WHEEL
micro_http_server-0.1.1.dist-info/METADATA
micro_http_server-0.1.1.dist-info/RECORD
