Metadata-Version: 2.4
Name: micro_http_server
Version: 0.1.1
Summary: a simple HTTP server using functional principles for Micropython and CPython
Keywords: httpserver,functional,asyncio
Author: Topi Kanerva
Requires-Python: >=3.8
Classifier: License :: OSI Approved :: MIT License
Classifier: Programming Language :: Python
Classifier: Programming Language :: Python :: 3
Classifier: Programming Language :: Python :: Implementation :: CPython
Classifier: Programming Language :: Python :: Implementation :: MicroPython
License-File: LICENSE
Requires-Dist: black ; extra == "dev"
Project-URL: Homepage, https://github.com/tkanerva/micro_http_server
Provides-Extra: dev
